{"file:///Users/katyrustrick/Documents/Website":{"assets/web/assets/jquery/jquery.min.js":"V5Dq1607onOXrt+j0mO4Zw==","assets/bootstrap/css/bootstrap.min.css":"9BHBNuK7MCraISCz6x1bww==","assets/bootstrap/css/bootstrap-grid.min.css":"kbYprkHMvvMG/ZJ2LsgHWQ==","assets/bootstrap/css/bootstrap-reboot.min.css":"//WhxWELTokJ3iPyIA2Taw==","assets/bootstrap/js/bootstrap.min.js":"aJXozWC2JkbOEkJgFYiPWA==","assets/popper/popper.min.js":"NiE4ESlZe/NNSKniYj4FyQ==","assets/tether/tether.min.css":"YhVaOUjL8Xsb9LQHyQq4Tw==","assets/tether/tether.min.js":"PlC291/0Eo8keLHUT4D9+w==","assets/smoothscroll/smooth-scroll.js":"/ilgR0JEXYwwmd70AnYqZg==","assets/dropdown/css/style.css":"s+S8lVC62P0BWFtgHpaNFA==","assets/dropdown/js/nav-dropdown.js":"9bGPRW1xT1/TQXobsnjO7Q==","assets/dropdown/js/navbar-dropdown.js":"4AZMGJuOfxUjEI1W5pEGCA==","assets/touchswipe/jquery.touch-swipe.min.js":"9g/wVGnRdXmW2F9BctT/TQ==","assets/ytplayer/jquery.mb.ytplayer.min.js":"UCqVnLtCcLPvcFiBkD5qfg==","assets/vimeoplayer/jquery.mb.vimeo_player.js":"GmfQhjxrSdOBpcDxHSmxjQ==","assets/parallax/jarallax.min.js":"bFQ4obzjiC9HL+BZ3/QknA==","assets/web/assets/mobirise-icons/mobirise-icons.css":"t/IrTIzfJvbDUoCV05F+7Q==","assets/web/assets/mobirise-icons/mobirise-icons.eot":"d1DWj4ts/6jfjnda7g4Q2A==","assets/theme/css/style.css":"6fOZEh7vGT496AAGYT74Ag==-VITbTf54ezV7Z7I/e4lZVw==","assets/web/assets/mobirise-icons/mobirise-icons.svg":"Yp5pSlGdnLgPdQLUa/Yv3w==","assets/playervimeo/vimeo_player.js":"iKSBqx5ssKBwubFGs8iVBA==","assets/web/assets/mobirise-icons/mobirise-icons.ttf":"sxxNoGToYfNN/LuoyTYkfg==","assets/web/assets/mobirise-icons/mobirise-icons.woff":"rcbBnBdGlGMmyU5U/bmzjg==","assets/socicon/css/styles.css":"q91aZJ04O5rzI1nJO9PRHw==","assets/socicon/fonts/socicon.eot":"MPSJKATRK38mcvpptQ55Tw==","assets/socicon/fonts/socicon.svg":"U1iRKoyNjKeR+mUJr3QbXg==","assets/socicon/fonts/socicon.ttf":"IHIkncvMbBJep0Ptli4Stw==","assets/socicon/fonts/socicon.woff":"5OoJHiBWPeGKNxNDiBvqvw==","assets/socicon/fonts/socicon.woff2":"Yi5MjejSv3HB65637JyuAQ==","assets/web/assets/mobirise-icons-bold/mobirise-icons-bold.css":"oCz4VsqVNHRevrgedUE3iA==","assets/web/assets/mobirise-icons-bold/mobirise-icons-bold.eot":"Sksg//CGhBJJQpIeycYzFA==","assets/web/assets/mobirise-icons-bold/mobirise-icons-bold.svg":"/6YZxrduGdMApfjQkLfW0g==","assets/web/assets/mobirise-icons-bold/mobirise-icons-bold.ttf":"Qvk3o2PlPgoJeppneihpNQ==","assets/web/assets/mobirise-icons-bold/mobirise-icons-bold.woff":"WKqhkmZeh8KpD1Tlv7dpEQ==","assets/formoid/formoid.min.js":"3j3qzwLV9Nl7bILSTiJhPw==","assets/images/munjiri-take-two.gif":"M8iNWl+Vlhp+8Hbt+x1qmA==","assets/images/favicon-128x128.png":"oAzBvz6uTPPxmVcRfJGHcw==","assets/images/hashes.json":"sokvMz9zLpP+kzRIVY4O+w==","assets/images/img-4875-1014x676.jpg":"a0Caz7mQ2yNabiKNxhzlUw==","assets/images/video-marketing-strategy-1466x978.jpg":"cSCoKBsAkMAs5Fh7cVKuIw==","assets/images/dsc09425-1014x677.jpg":"xlCSX3HDb975YvTgFhWjzQ==","assets/images/dsc00691-1576x1053.jpg":"7071B3UgSHG6CUpUaUxCjg==","assets/images/munjiri-desk-1014x717.jpg":"JBKea43EeoELxt/X1fkt4A==","assets/images/dsc02724-676x451.jpg":"xjJZSf84zlbZwHNbyYDz8Q==","assets/images/dsc07091-1-1014x676.jpg":"8g3l4VCHvo89uhRAInuPFA==","assets/images/dsc00683-676x452.jpg":"fSbcJFJzCpCcO0F1laqU2Q==","assets/images/soul-design-jewellery.still006-676x450.jpg":"Bfxzkdx/scV5hDwee+Ft7w==","assets/images/munjiri-1576x1114.jpg":"cfoMJJT1gp7MqasWZVMwJQ==","assets/images/katy-eugene-1-848x848.jpg":"16XviKC4F5gh+OE0/ngt/g==","assets/images/dsc05033-676x380.jpg":"T3Feq1qNuiCLBrgw4U9kfA==","assets/images/1-676x381.jpg":"z7QCfNNV+QTH99agyGN5TA==","assets/images/adorned-10-676x380.jpg":"cr0qsNwlSFEpJG8cX9XOnQ==","assets/images/adorned-7-676x380.jpg":"owijR6+5xDkZXIfRf1MCKg==","assets/images/adorned-12-676x380.jpg":"TfmPzZc7LaoY/p7h6Lc83g==","assets/images/dsc09562-676x380.jpg":"VZ5e3xbkiTMWx4XSxbTZhg==","assets/images/dsc05568-676x380.jpg":"aXabZcwtstz9S/6MZYi0FQ==","assets/images/dsc09565-676x380.jpg":"b0dzTIHbv2KcIirAhrViyg==","assets/images/dsc05052-676x380.jpg":"VPq2NI9TRCHg9UQO7sDz2g==","assets/images/dsc05533-642x361.jpg":"+S2jXGenMGUH2u79A5xf2w==","assets/images/dsc05398-626x352.jpg":"n7/Z0ik++o7XuLtSUp8iaA==","assets/images/dsc00768-1104x738-1-626x352.jpg":"fj27gO5LrY0b8F0AZ16U4A==","assets/images/dsc05573-676x380.jpg":"mdIesLZX3hVY4I4vYNsgUA==","assets/images/dsc00630-626x352.jpg":"vMgq4eAr3aCO+4EUD5Qwnw==","assets/images/dsc00378-676x380.jpg":"u4lnkOZ2RnUOxpAlDfXR0Q==","assets/images/dsc00599-676x380.jpg":"xbJl3A9n2HLTcvk5H+8trw==","assets/images/2-1-676x380.jpg":"MtmyiknI2W9B49jj/TDl6w==","assets/images/dsc00475-676x380.jpg":"ARP9aF1d2fRvB2x2kQg0IQ==","assets/images/1-4-676x380.jpg":"WXp4OuezCXLbik3EJpJrkQ==","assets/images/dsc08832-676x380.jpg":"1VYQPtnhIBAUHgZpbOZfQA==","assets/images/dsc09020-676x381.jpg":"1uSl72IzDhGzh3SBFfq+OQ==","assets/images/dsc08560-676x380.jpg":"CeFSc44TBpXTh788LZB3tg==","assets/images/c0298.00-00-14-14.still012-676x380.jpg":"o8nPWhM+CBFOs4z9QMXECQ==","assets/images/c0298.00-00-32-05.still013-676x380.jpg":"tpzXLB0uOHdsTSnPbxLrRA==","assets/images/c0298.00-00-20-08.still022-676x380.jpg":"Y4PFWzq7yaavv4s4QitRBg==","assets/images/soul-design-cpt-sequence.00-01-00-06.still008-676x380.jpg":"Sc8mo+5fAGzabWOqrtajyA==","assets/images/3-1-676x380.jpg":"gmeAWUPMAxkTdq0lca/Xnw==","assets/images/soul-design-cpt-sequence.00-01-17-12.still006-676x380.jpg":"5YsQvr1c3fxZjAFvWAODoA==","assets/images/soul-design-cpt-sequence.00-00-48-16.still005-676x380.jpg":"6lqLJeTjQw//d3LHCtu8KA==","assets/images/dsc07650-676x380.jpg":"KHFS6I0En8kYzFUE1PkGzA==","assets/images/dsc07588-edit-676x380.jpg":"nesimJRkwfFSpJciCM6WPA==","assets/images/dsc07684-676x380.jpg":"845SBDW3dBi/zfiLw1Zy/Q==","assets/images/2-556x313.jpg":"8z0kh43trqO+ekTGuajS4w==","assets/images/dsc09556-676x380.jpg":"0TnnIcXNXgkGPxPLX+etPw==","assets/images/1-676x380.jpg":"oJlx/7vH9NnWKfFRygwnUg==","assets/images/golden-hour-556x313.jpg":"JlXz9OCUUGEHclt5ADIn9w==","assets/images/composition-676x380.jpg":"4iY2Rejf/Gn7S1Hin26Auw==","assets/images/leading-lines-676x380.jpg":"TedSxAjXro7/dNsAxTsaMQ==","assets/images/african-bats-sequence.00-01-17-09.still004-676x380.jpg":"QaYEDaajEcNU2HXhwCO3NQ==","assets/images/framing-676x380.jpg":"xSkAqnLO4ZaHlQnMq5VfBA==","assets/images/african-bats-sequence.00-00-11-03.still001-676x380.jpg":"D9HY78guYos8VZPMab+DjQ==","assets/images/img-540-556x313.jpg":"/5p0buVZQy6+mlWm/rFC2A==","assets/images/img-1575-556x313.jpg":"7L19pTzm2ISz+MKR5UHA4Q==","assets/images/african-bats-sequence.00-00-25-09.still003-676x380.jpg":"4ZjH1fIx3QWu6FwFruh2cQ==","assets/images/img-0344-3-676x380.jpg":"ON5kKQfHntWa3znOazgJKw==","assets/images/img-477-676x380.jpg":"mCiN3hgU2Lr3DTZNB4PInQ==","assets/images/img-1307-556x313.jpg":"mDSw6kUhW8vwrAl4bf579w==","assets/images/collingwood-norris-sequence.00-00-01-02.still009-676x380.jpg":"fjAinqMeF4JJ4bxJRakQDQ==","assets/images/img-407-676x380.jpg":"3RM/h2xoU75KkCJkRieT+w==","assets/images/collingwood-norris-sequence.00-00-02-20.still010-556x313.jpg":"JdsTUc3hK34BLoSr1qJFdw==","assets/images/collingwood-norris-sequence.00-00-05-10.still011-556x313.jpg":"NiGyGI+FI376itFC9R3gsg==","assets/images/african-bats-sequence.00-00-25-09.still003-676x38010.jpg":"4ZjH1fIx3QWu6FwFruh2cQ==","assets/images/dsc01419-edit-676x380.jpg":"4Pw02f5oNWOiBD5POvoFCA==","assets/images/wildlife-africa-final-2-676x380.jpg":"UXUbqZJCtF0TrSxXVP3Rmw==","assets/images/pamoja.00-00-11-01.still007-676x380.jpg":"QCMJb2MNYfWB+87tsuG1Ng==","assets/images/sequence-01.00-00-12-08.still003-edit-676x381.jpg":"dQLPekBjDKvFrGeG4EAbcw==","assets/images/dsc02210-edit-676x380.jpg":"NKdDER1GORl/kfWltB3tGQ==","assets/images/pamoja.00-00-00-21.still008-676x380.jpg":"3XOMqf6dGIhWk0yTuxqPkw==","assets/images/soul-design-jewellery.still006-980x551.jpg":"rHhQu1eFMmkrkSp/TfueAA==","assets/images/together.00-02-21-04.still010-1576x887.jpg":"3x3lgycQmWBqRonubym+PA==","assets/images/together.00-02-23-00.still011-1576x887.jpg":"zYwXQ8GMg48He57Ucx2q3A==","assets/images/1-1-676x380.jpg":"Xe4kgjDY5NXZ9sp07Aq3uw==","assets/images/soul-design-jewellery-still003-1320x743.jpg":"DlwffiJ0gadXj4i854k2vw==","assets/images/together.00-02-16-05.still008-1576x887.jpg":"DLhsRjJnd6aBGH1W54R14A==","assets/images/together.00-02-17-07.still007-1576x887.jpg":"3LEM6zg0rGP2Z1RMNmaG1Q==","assets/images/together.00-02-27-23.still014-1576x887.jpg":"xdtlUt5C0C/xHB+I/JaIWA==","assets/images/soul-design-jewellery.still004-1576x887.jpg":"U3Y7uEjXD1D9WiZxVpCKtw==","assets/images/together.00-02-39-00.still016-1576x887.jpg":"GO9i2Dxt4HqKqLhSLVo5UQ==","assets/images/together.00-02-33-05.still015-1576x887.jpg":"nkeYXtBDY6rrrElD63/tmA==","assets/images/together.00-02-26-22.still013-1576x887.jpg":"M1FrDYSsOBJgx82peHv4lw==","assets/images/together.00-02-42-19.still018-1576x887.jpg":"ecQzJDCK4/5zkKKh9zoHYg==","assets/images/soul-design-jewellery-tools-1092x729.jpg":"MbO0U+l4NUVWaosp5oTRnw==","assets/images/soul-design-jewellery.still005-1576x887.jpg":"A5c0B9SdBtPb990itl3jug==","assets/images/soul-design-jewellery-cuff-816x1222.jpg":"zCzVSq4xzsJDzyfiANeRrQ==","assets/images/soul-design-francis-and-alphonce-1158x1734.jpg":"hmLVdOs/TZiNv2rQtXgEAA==","assets/images/soul-design-cutting-1282x856.jpg":"pN27VDZABhfKYPBah569SA==","assets/images/soul-design-hammering-1658x1107.jpg":"J8NgyfTmZ5NMRnybKAZL2A==","assets/images/soul-design-bonniface-934x1398.jpg":"yTHcmTeE6w3sOmX04cqoQA==","assets/images/soul-design-process-906x1356.jpg":"xQxEJZ3L8KYI8LXyzG4GDg==","assets/images/soul-design-offcuts-1310x875.jpg":"pnWX4OOdvipkZ01xl5wo1Q==","assets/images/collingwood-norris-sequence.00-00-01-07.still013-980x551.jpg":"f6uEevEQD9iSLF8vZNseqQ==","assets/images/collingwood-norris-sequence.00-00-33-17.still019-1576x887.jpg":"2yl01HjV3wqsrb0BZk3Vjg==","assets/images/collingwood-norris-sequence.00-00-28-01.still018-1576x887.jpg":"kKI4rxvudrJi+CsL3shsTw==","assets/images/collingwood-norris-sequence.00-01-58-14.still029-1576x887.jpg":"3t94aVK0tRMyKvfgZa5Ybg==","assets/images/collingwood-norris-sequence.00-02-11-08.still030-980x551.jpg":"TsoJglNTxQPBsoT87CGXXA==","assets/images/collingwood-norris-sequence.00-00-15-17.still016-edit-1576x887.jpg":"mPbm8JDz3Vp2mmrdj7wIOQ==","assets/images/collingwood-norris-sequence.00-01-28-17.still025-1576x887.jpg":"itrlzld+YA65dPCuXQmWdQ==","assets/images/collingwood-norris-sequence.00-00-05-01.still015-1576x887.jpg":"7ZAQawhVuOLNlDoVO7w1XQ==","assets/images/collingwood-norris-sequence.00-01-21-01.still024-980x551.jpg":"/HMX7BXNI1ajLDMGwWu5WQ==","assets/images/collingwood-norris-sequence.00-01-07-11.still023-1576x887.jpg":"9HsnhbgISXVqxmXdU7AH4A==","assets/images/collingwood-norris-sequence.00-01-50-24.still027-1576x887.jpg":"wYbIfHk88aF/+LEnbLqJJg==","assets/images/african-bats-sequence.00-01-17-09.still004-1320x743.jpg":"WGRPc/GByu3Eb+YiZCfxjg==","assets/images/african-bats-sequence.00-00-25-09.still003-1320x743.jpg":"yWG0sDQWf459/Zl+MzmN7Q==","assets/images/african-bats-sequence.00-00-14-23.still002-1320x743.jpg":"NUuETCoQI3WrpSOEQIZi5w==","assets/images/african-bats-sequence.00-00-11-03.still001-1320x743.jpg":"8VeVjwRaRE+lPRoUWDL8zg==","assets/images/abc-final-video.00-00-02-09.still002-1320x743.jpg":"/+iLi7dAJIbCpvBhzs0vqA==","assets/images/abc-final-video.00-01-01-16.still008-1020x574.jpg":"AzsbsedotSx33TL9D/k68Q==","assets/images/abc-final-video.00-00-53-08.still005-980x551.jpg":"1OB+iKy1GbWcE/Su8CMILQ==","assets/images/abc-final-video.00-00-08-05.still001-1320x743.jpg":"VcPXpS9OsRpRoXvLTUklxw==","assets/images/img-2095-1576x1051.jpg":"kX6Gq7EePouxUtiMsvdXXw==","assets/images/abc-final-video.00-00-55-05.still006-980x551.jpg":"KgveUuIyNMtcBrQOyPqaoQ==","assets/images/abc-final-video.00-00-58-05.still007-1020x574.jpg":"/M8XdDHhz/P6zpPPEefypA==","assets/images/img-2980-1576x1051.jpg":"Dpj7A6DsvwX/oAP3JrCifQ==","assets/images/dsc05285-1576x1053.jpg":"ZdAcLvSzOFK66zcKxkQB4Q==","assets/images/img-4980-1576x1051.jpg":"ZtUmW9XRGc6rkgCVNdCoMw==","assets/images/img-957-1576x1051.jpg":"7Qx9E2ODTGBX2rXbmR4mTg==","assets/images/maya-856x1284.jpg":"4RI7qCoHkoiaMnJa1EpmNA==","assets/images/img-6611-1576x1051.jpg":"Apc4CKIDJEZRuYHh66RJ/w==","assets/images/img-581-1576x1051.jpg":"bXpgMEupZBFWHEQudFAJHQ==","assets/images/img-1307-1576x1051.jpg":"7d/AB/AqOUBIpkAuYWoAVA==","assets/images/img-469-1104x736.jpg":"4CPjJfBeVxLb5J3wIeZF0A==","assets/images/img-407-1104x1656.jpg":"LFjxWy02iDCLMUCq1+WycA==","assets/images/dsc08617-1576x1053.jpg":"7NoYbY5NpTzsqq2vykJGoA==","assets/images/maya1-1088x1632.jpg":"aqJB0jplwlSjaJh6oqg6FA==","assets/images/img-431-620x930.jpg":"I9GSA9wpoJuQ8RVOLt9A8g==","assets/images/img-467-620x413.jpg":"VbX5kjbp0Og8nb4yoPWLRw==","assets/images/img-390-1092x1638.jpg":"xgl2vEYzDlMMqlMlD3G0kA==","assets/images/img-533-1576x2364.jpg":"fX/foy4XK28TV8GtYeF4NA==","assets/images/golden-hour-1576x887.jpg":"ho67GcK/9pKvo1GBgyACmA==","assets/images/img-3120-1414x795.jpg":"TfOBLSHDYL5eosddbbb9Xw==","assets/images/screenshot-2020-07-08-at-10.02.15-copy-980x551.jpg":"47fBTdwf0e3bMYBTj+rNHA==","assets/images/img-419-1092x1637.jpg":"vMOK7vn/u8t7eTZLWdt39g==","assets/images/dsc01419-edit-556x313.jpg":"4ulcKrjh0BpsD1egEfiYgw==","assets/images/screenshot-2020-07-08-at-09.52.12-1320x742.jpg":"EzNXEZejCe1J1NVr9C5+PQ==","assets/images/composition-556x313.jpg":"BM2+tjuRnbjizHh/SItoWA==","assets/images/composition-980x551.jpg":"agWyQiiJAv1/pGrIotMloQ==","assets/images/leading-lines-980x551.jpg":"9oRMSZNw0FPY0D1vQBjZvg==","assets/images/framing-1576x886.jpg":"AUilc7yHphJyvYM0CYvdwQ==","assets/images/depth-1576x887.jpg":"/R8oIVl89t2feblTZK8O1g==","assets/images/dsc08014-1576x886.jpg":"nV27uTn3o4uNvzAYUecrPQ==","assets/images/watch-movies-1320x742.jpg":"I+dabZuG7pG/wssSZ0zN+A==","assets/images/nonthu-774x1161.jpg":"7OdXMDoJzExz+fzRHqH8gQ==","assets/images/soul-design-jewellery.still005-938x625.jpg":"+2RoeqtDsP275QF0hs7O8w==","assets/images/golden-hour-1-556x313.jpg":"ryOO7gDPAZdsQVEmqIM+Iw==","assets/images/soul-design-jewellery-tools-1062x709.jpg":"KhskrhH5Zxh6uTf/dbSJfg==","assets/images/rule-of-thirds-1020x574.jpg":"1x4uwSkA2uip+7S7duQxrw==","assets/images/dsc04922-1086x1626.jpg":"acpgMPrZIkgNU8O83qcGeg==","assets/images/img-1313-626x939.jpg":"Y58GSN/Q1k35D3Zh/HNopg==","assets/images/dsc04976-1282x1919.jpg":"GR56yrc9z1dznxq2Byjqtg==","assets/images/dsc05227-1314x1971.jpg":"dbYrvrc2aly3y2uIhtEfuw==","assets/images/collingwood-norris-sequence.00-01-21-01.still024-774x516.jpg":"vd1lIvBf+jZhSNuCRWDJ+w==","assets/images/collingwood-norris-sequence.00-00-01-07.still013-650x433.jpg":"7CHPVX5iswE798X5zVdvLw==","assets/images/collingwood-norris-sequence.00-01-07-11.still023-1206x804.jpg":"fgawxIIwWLF1wfpl7K2n9A==","assets/images/collingwood-norris-sequence.00-00-28-01.still018-782x522.jpg":"QHPrslSIl8du5DLj8mdZKQ==","assets/images/dsc08123-1316x879.jpg":"ZTubfDIE3UJbEqJ29GjbrA==","assets/images/dsc08169-900x1347.jpg":"crMbL4m8yeMS+YHC2zbiLw==","assets/images/img-1368-938x1407.jpg":"v1fcQmtqS9l+Kt4k8noAWA==","assets/images/dsc08135-1576x1052.jpg":"wgrEPHpaWHb7T9XOY0sP/w==","assets/images/111-824x549.jpg":"PqPUSkOmDQSi8fq706sqQw==","assets/images/dsc08030-1392x930.jpg":"1pYVasz9wm/bBd2Lh5qGVg==","assets/images/collingwood-norris-sequence.00-00-19-08.still017-866x577.jpg":"2GfXGKj6ffkOZKJuPMqbDQ==","assets/images/dsc07983-824x1234.jpg":"vsRjJtTvTT8x39xVQaB4ig==","assets/images/dsc08116-942x1413.jpg":"82mb4rRl0BeXB4wWZ2KVOw==","assets/images/dsc08014-1100x735.jpg":"VH0zEiWJEQ2qs02KtTtxIA==","assets/images/dsc02210-edit-1282x855.jpg":"nPxjKE3wKGs/ghdLiVhiBA==","assets/images/333-1392x928.jpg":"sH479u801d8bJEi4VB6KXA==","assets/images/dsc02219-934x1401.jpg":"X6fORH+kDX35OEY9mZUWRg==","assets/images/dsc02552-edit-1576x1051.jpg":"OmLPuPVhljGlsWsDnirwVQ==","assets/images/dsc03560-copy-676x676.jpg":"Q+ijag0jbgqecvA5oKFqwg==","assets/images/dsc02295-edit-904x604.jpg":"OzAFySpC3h6x4zEOeTeyKQ==","assets/images/dsc02330-1312x1964.jpg":"gpPgyOGVqr4XPClVIXqeug==","assets/images/dsc03563-copy-676x676.jpg":"u8rfNyCyR8JkYfvI+0LY2A==","assets/images/dsc03565-copy-676x676.jpg":"KZ8uiC+HxxRUJdbj2iJgeQ==","assets/images/dsc02438-1302x1949.jpg":"vGIlZFgBYEJpfCR/kU4+QQ==","assets/images/screenshot-2020-09-01-at-15.00.21-1316x877.jpg":"4AGuSlWsrDf/4h2badvc8w==","assets/images/dsc02843-918x1374.jpg":"ROHr/BhG7Vg21ZDp20+I5Q==","assets/images/dsc03458-972x649.jpg":"Ua/mC5p3VknSXFOoYa9hSw==","assets/images/dsc03368-900x1347.jpg":"6h/1WwfD0QNCQpA0C9DSaw==","assets/images/dsc03123-1576x1053.jpg":"56ovlWrOt9mkjfTUofbCsA==","assets/images/dsc02734-1148x767.jpg":"8rlwZQSXKycC4q/PmWIoxQ==","assets/images/dsc03508-1310x873.jpg":"jd5/je+HKkVM/UwG6JLegQ==","assets/images/dsc03403-906x605.jpg":"8R+8FkCt6tvz6ADK1WzLZQ==","assets/images/dsc03091-1340x2006.jpg":"1SjRv4WRJM+/h3rjI5dKBQ==","assets/images/dsc03012-1290x862.jpg":"o1HL7Zo4ukAcIkv8pG3oog==","assets/images/dsc03373-1374x2057.jpg":"vJ2V2fAzl6y9h1V+CBJ3Fw==","assets/images/dsc03322-842x561.jpg":"cVAezc4/To8DADf5h/cM1Q==","assets/images/dsc02860-1198x800.jpg":"yTU/OoVDHm1GxrVolrkn2A==","assets/images/dsc04153-676x1012.jpg":"LEKhCIPEBlSYkmulOdEdlw==","assets/images/dsc03978-1-676x1012.jpg":"VWjpNGr0jmeL+xwOyWKtfQ==","assets/images/dsc04169-676x1012.jpg":"qbVXcioxKk0uZayK8V0kLg==","assets/images/dsc04281-836x1251.jpg":"aGCgIqWJLigjPxOr/V1tdg==","assets/images/dsc04303-782x1171.jpg":"acpHU8uguZp+fvpBJOzb1g==","assets/images/dsc04202-866x1297.jpg":"KOl9vgfEWK91ZitZOau5hQ==","assets/images/dsc04021-676x1012.jpg":"FD5YhpcK1cEN5xG+SI+gKA==","assets/images/dsc03952-676x1014.jpg":"rHdH5T5xvmPIE9h1S7TmEA==","assets/images/dsc03993-1-676x1012.jpg":"c9E+oUTKfhjwPNhn8vJZLQ==","assets/images/dsc04154-960x641.jpg":"rslCnOllEcCJoBlxPfZf1Q==","assets/images/dsc04250-1130x1692.jpg":"mNFZUXBr3eXrCfwZCmKseQ==","assets/images/dsc04190-936x1401.jpg":"7R2x4ODEWL9ssrh+35P/eA==","assets/images/dsc04188-1284x1922.jpg":"E+LCBZ+ibkvuw1cwaQtyAA==","assets/images/dsc02210-edit-1576x886.jpg":"T4JZ7Hp+NuAAwAg6LP6TNQ==","assets/images/pamoja.00-00-11-01.still007-1576x887.jpg":"OsIlX8dnrbZuIoJxn3ok2Q==","assets/images/pamoja.00-01-28-02.still006-1576x887.jpg":"3ycwf1SfxQ7DdVd0lzE61g==","assets/images/pamoja.00-01-29-06.still010-1576x887.jpg":"OyieQquKCIlOHqu323kZvA==","assets/images/1-1576x1051.jpg":"E6u6jvRW5aaf52LDTAec/w==","assets/images/dsc05059-836x1252.jpg":"H1QzkdqaVL49W/QBRoDzPQ==","assets/images/dsc05045-712x1066.jpg":"vJsG7ZKdlnhUWDSqQ4dCQQ==","assets/images/dsc05033-626x937.jpg":"gOkP29+ptft1J67XuMgKHQ==","assets/images/dsc05052-828x1240.jpg":"4KN3Th9/kiUr7xY95FN05A==","assets/images/dsc05119-836x1252.jpg":"DncuMA27FlAHe4OAwgDvCQ==","assets/images/dsc07091-1576x1051.jpg":"3Vmww8MxBt9sAVefhuUgpw==","assets/images/dsc02724-960x641.jpg":"67MYBMt35vvTfR5NsdiQPQ==","assets/images/screenshot-2021-01-07-at-12.44.03-556x313.jpg":"YT1AuVlUgUN2eo1xb1VA0A==","assets/images/screenshot-2021-01-07-at-12.44.17-556x313.jpg":"VxXNIxxWrikLOA1uhVvT3Q==","assets/images/screenshot-2021-01-07-at-12.45.43-556x313.jpg":"+gIhb7pVNnGYJgeFCJ0VhQ==","assets/images/dsc04967-960x1437.jpg":"HhYEsFBYFQ6K/tAcWJU00w==","assets/images/screenshot-2021-01-07-at-12.58.01-676x380.jpg":"con2IRCwhbfOl7cK+x8kmQ==","assets/images/screenshot-2021-01-07-at-13.02.40-676x380.jpg":"K8jVM8APfdrgkL/bhdO6bA==","assets/images/mkale-school-video8-676x380.jpg":"J5WwUQNhzZtHxTGY/BymCg==","assets/images/pamoja.00-01-01-04.still009-1576x887.jpg":"Eb61Y7YbzyEXJJaeqLxT9Q==","assets/images/mkale-school-video7-676x380.jpg":"XTmvXXc1nQJceUUCNmIgvQ==","assets/images/screenshot-2021-01-07-at-13.01.25-676x380.jpg":"rDyCo8xjxdAPTOkACzd/Ew==","assets/images/mkale-school-video6-676x380.jpg":"UZlPOrR3JonjwzmrLN1SiA==","assets/images/dsc00682-676x380.jpg":"kKqHnSU9XH4otH2ZJQ8PBg==","assets/images/img-0344-4-676x380.jpg":"ON5kKQfHntWa3znOazgJKw==","assets/images/dsc09104-2-676x380.jpg":"oGc6TSLWAT4fqjfsZwYG3g==","assets/images/new-.00-00-20-23.still010-676x380.jpg":"ZOxcKkZ9WgpnYuruejBV6g==","assets/images/img-478-676x380.jpg":"mCiN3hgU2Lr3DTZNB4PInQ==","assets/images/dsc03123-556x313.jpg":"PkylUjrkrFTLsE0uEoXdxA==","assets/images/screenshot-2021-01-07-at-13.20.50-676x380.jpg":"7FqEwZdDaYPFkPEKrw2RSQ==","assets/images/screenshot-2021-01-08-at-08.55.04-556x313.jpg":"O8RZSFiwDyTStBvobYd1jQ==","assets/images/dsc02724-556x313.jpg":"wXS7llNh+V2mFed5QAh0Xg==","assets/images/pollination-project-sequence.00-00-33-00.still003-626x352.jpg":"rFcULfmSjHobL6Bmutq4Gg==","assets/images/dsc02860-556x313.jpg":"CCzj6Br28bbYAq1X88xIlA==","assets/images/screenshot-2021-01-07-at-16.41.05-556x313.png":"abbDfn9gRetT5Kkn1V14rQ==","assets/images/screenshot-2021-01-07-at-16.46.32-626x352.png":"Hu/HWeD702MoEbV7AuMdlA==","assets/images/dsc04256-1152x1725.jpg":"ltv5V/sG5ulH/eFRZ/YJgQ==","assets/images/screenshot-2021-01-07-at-16.29.49-556x313.png":"Y5xtgqmvq1mR+GA2uGWG8g==","assets/images/screenshot-2021-01-07-at-16.30.21-556x312.png":"oBlmhWPCVSfaGMFQ0GHE0w==","assets/images/screenshot-2021-01-07-at-16.40.54-copy-556x313.png":"Ex5Ws+qKEY9SkwYLyTyv0w==","assets/images/img-408-676x380.jpg":"3RM/h2xoU75KkCJkRieT+w==","assets/images/trial.00-01-16-02.still004-556x313.jpg":"r2wcNV+WPo9QTUyASHoRZg==","assets/images/screenshot-2021-01-07-at-16.29.59-556x313.png":"Q8waUr9AT9ty0EF06LxO2Q==","assets/images/screenshot-2021-01-07-at-16.24.27-556x313.png":"zvP/whTnu9J58982gxScOQ==","assets/images/screenshot-2021-01-07-at-16.26.32-556x313.png":"xZ+o57Sk45/q7aBneQNtqA==","assets/images/collingwood-norris-sequence.00-00-01-02.still009-1-676x380.jpg":"fjAinqMeF4JJ4bxJRakQDQ==","assets/images/collingwood-norris-sequence.00-01-21-01.still024-1-676x380.jpg":"dhd6tvkSUH+vZNnQR9wJtg==","assets/images/collingwood-norris-sequence.00-00-28-01.still018-1-676x380.jpg":"dBqwEtyMQDfYzGLsr72ZUg==","assets/images/pamoja-1.00-00-53-04.still004-676x380.jpg":"En27cm0g3JZJJRKC4WMBxg==","assets/images/dsc01024-676x380.jpg":"iZgKfoJ9THzrz+arsJa1yg==","assets/images/5-676x381.jpg":"q49/UbANZM211QVeJwtGIg==","assets/images/2-2-676x380.jpg":"M1kWq7AayfMpCRmd0lffaw==","assets/images/1-2-676x381.jpg":"I/1ndrJzYJkNFswlM3wB/g==","assets/images/together.00-02-39-00.still016-676x380.jpg":"diYmZHycYE+GfyPaoLg9Kg==","assets/images/soul-design-jewellery.still006-676x380.jpg":"vKoFeUViwfMGkq2GYftNOQ==","assets/images/together.00-02-27-23.still014-556x313.jpg":"g77V3fpQzM4tCQ7d7lNKpA==","assets/images/screenshot-2020-09-01-at-15.00.21-556x313.jpg":"d+j6KeQu+EL5ldpqWXnVmA==","assets/images/dsc02438-556x313.jpg":"FGDAHG8Ryoqtlm+60bTtQQ==","assets/images/111-676x380.jpg":"tFe7S0GaT03FH39no2LYjg==","assets/images/pamoja-1.00-00-22-10.still002-676x380.jpg":"6tzId9P/c9mtn2CPgmOg+w==","assets/images/dsc08014-676x380.jpg":"EE9jkbuLSzvjk0bgXqFYIg==","assets/images/dsc03869-676x380.jpg":"8ywjKRFdGWfB+eVQagLDKg==","assets/images/dsc03887-1-676x380.jpg":"jH6NKMTvGTil8z0TDbld6A==","assets/images/dsc03863-676x380.jpg":"RLkITIqukhou7+vKNZjNKg==","assets/images/dsc04281-874x1308-2-626x352.jpg":"VxB74hhkIHR1Hws7qOEA2w==","assets/images/dsc04250-1130x1692-2-626x352.jpg":"eNkvAgHxLRWzfH/aVOmcFw==","assets/images/dsc08135-676x380.jpg":"Uuj9AcATL71DrfFT8K8YQQ==","assets/images/2-676x380.jpg":"zFobgkOBKpLovWLrmjYLaA==","assets/images/dsc02219-556x313.jpg":"caD0kELNaGlosJ69MD7pcw==","assets/images/dsc00651-1754x1172.jpg":"JOKwWezejC6dnhyGXCcSwg==","assets/images/dsc00824-1020x681.jpg":"KvvQecP0E0YMUfHqzvviHg==","assets/images/dsc00660-1092x729.jpg":"uYZfetn6VtslwgPWQOQM9g==","assets/images/dsc04188-1082x1620-2-626x352.jpg":"uaxEXv/wieANf/yxot7nqQ==","assets/images/dsc00768-1104x738.jpg":"qle/wlCtaD/r80Y4vfotjg==","assets/images/dsc05327-620x928.jpg":"htgQ/H+m/6geWFyrnPyiCA==","assets/images/dsc00630-1104x1653.jpg":"6OoxgL5u0qUQFXY62wV/uA==","assets/images/3-676x380.jpg":"Vmelj2mE/X5m/NgkZNS7uQ==","assets/images/adorned-19-676x380.jpg":"q8BZUwcst6AJqwc3cp8b6w==","assets/images/dsc05398-1104x1653.jpg":"L8MgPMb0yhKD3etnEotNBg==","assets/images/dsc00867-1104x737.jpg":"6Ra2g9gCnyg2bkG5PWWjCg==","assets/images/dsc00781-980x655.jpg":"0xckqJgbRFG4zO3KUtU3OA==","assets/images/dsc05354-620x928.jpg":"0+0v/5AuYNor+CeTqTnF7Q==","assets/images/img-540-980x653.jpg":"d+LmeYEglYLaZ65sAS8uXQ==","assets/images/dsc05399-1092x1635.jpg":"qr+xDhjRz7HAZt5VCPLpzQ==","assets/images/img-0858-2-620x930.jpg":"ulAm7neIBo2hVSjo3bnZGg==","assets/images/img-1575-620x413.jpg":"0TwMvkVNNyrQsCoYcEVjOg==","assets/images/1-3-676x380.jpg":"NOZl02T9hNQpjHVS8rIEcw==","assets/images/img-826-1020x680.jpg":"kA6PEn+LyyX/feD8ftZwUw==","assets/images/img-417-980x653.jpg":"LECMRtUe60LG4CLBE4ji0g==","assets/images/img-1307-1020x680.jpg":"DMcIDSyN6ZN64zd4VgEAJQ==","assets/images/img-749-620x930.jpg":"pRwJtoU1da2Q81Op75eUtw==","assets/images/img-1117-1092x728.jpg":"k6USDt+tFlZAQk+Icg+UFQ==","assets/images/img-1133-1020x680.jpg":"mRohSa29huag9E2Ms+AeoQ==","assets/images/dsc01419-edit-676x1202.jpg":"ITXhajoA5rd1INYSz8hbSQ==","assets/images/img-1120-1092x728.jpg":"8aIZWtBA+3v3RLa491YzdQ==","assets/images/img-1305-1020x680.jpg":"QoRFrDxHfC9YMfeXmmD6yg==","assets/images/sequence-01.00-00-12-08.still003-edit-676x1202.jpg":"8Rm8m03fjXuN4YwNA73Vpg==","assets/images/img-591-1092x1638.jpg":"gaTxX6rIjsYlK/hBztep+g==","assets/images/dsc01444-676x1202.jpg":"yyiudj+2BBCkP+R+8o3pjw==","assets/images/sequence-01.00-00-42-05.still006-1046x1860.jpg":"x3COxSr4QN2WqbvhbZ8R8Q==","assets/images/sequence-01.00-00-29-20.still007-1046x1860.jpg":"zAsO+SW1piB/cxlG63/EyA==","assets/images/sequence-01.00-00-21-12.still010-676x1202.jpg":"77GmLErF81ubbfKySgb5UA==","assets/images/sequence-01.00-00-45-14.still009-676x1202.jpg":"bBoSIPD4kn4/FWlmiJOP9A==","assets/images/sequence-01.00-00-07-10.still002-676x1202.jpg":"AWz7L44WvpCbSpuKvC7gPQ==","assets/images/sequence-01.00-00-11-08.still008-676x1202.jpg":"DxxTjX/uO3hcBFY0HzR8Bg==","assets/images/c0298.00-00-14-14.still012-1576x887.jpg":"/hBlqdkxtRkIbhC4fThfTg==","assets/images/c0298.00-00-38-10.still015-1576x887.jpg":"E+mYR2DATenpbpWsEC/MKA==","assets/images/c0298.00-00-36-17.still014-1576x887.jpg":"H2TP2rc2AXIsDRKai6aQxw==","assets/images/dsc05646-1576x1051.jpg":"fT22HqEk3szaoNj3a8hORw==","assets/images/dsc05573-854x1281.jpg":"Tz89caYW6bW8qs2YZGOHEA==","assets/images/img-3989-958x639.jpg":"yihhVJ+VAuBoEeR+2AQWew==","assets/images/dsc05533-642x963.jpg":"3oKKsPzIusD+kqjNIaiyxQ==","assets/images/dsc05513-684x1024.jpg":"l7iTGg3R8+pGoNENt3zUPw==","assets/images/img-3942-1022x1533.jpg":"ft7aHMPn2SVnL8zWcLgCqg==","assets/images/img-3954-1028x685.jpg":"GvrgZEQPfr0glV41WCIizQ==","assets/images/dsc05568-858x1285.jpg":"bHXpyqIIFYALQ1uX40D5xw==","assets/images/dsc05680-1070x715.jpg":"IgTwkpu1+B/PF2cxCgp6Yw==","assets/images/dsc05678-660x988.jpg":"iAOwIF/rFwYSw8ti/Xz6tQ==","assets/images/dsc05613-920x1377.jpg":"mZplZyvTijmVGdIi6Ukfjg==","assets/images/dsc05660-696x1042.jpg":"e+rAcriLbHVavhYYD91oUg==","assets/images/dsc05520-830x554.jpg":"O8yIANP1G2LQrHvTf0VcSg==","assets/images/img-4015-926x1389.jpg":"4qPhsgNItrwcNvIPIt4gIw==","assets/images/dsc05537-962x1443.jpg":"Ck0Njkyelu2xOAnTKc2+og==","assets/images/dsc05561-946x1419.jpg":"4G8oK9woirnrHHtT4jW+oA==","assets/images/dsc05644-774x1159.jpg":"w7rtDCLm4sJMCgZclCGXlg==","assets/images/dsc05676-938x1404.jpg":"uCjD9rleMFsvmzPZYDbwyQ==","assets/images/pamoja.00-00-24-06.still014-676x380.jpg":"7tw+8Rd4DcQ9MCXcQ+xKTQ==","assets/images/pamoja.00-00-28-01.still003-676x380.jpg":"+pinO/8gylTd+YXMQLKmIQ==","assets/images/image-875x945.jpg":"rYIVAk9p94h1kY/NsgqY9w==","assets/images/pamoja.00-02-45-21.still008-676x380.jpg":"8huKqW7f9oJn5oA0wxVIlA==","assets/images/dsc09764-676x380.jpg":"a8eM2gqL4FEFTzXjY/uweQ==","assets/images/dsc09704-676x380.jpg":"zha20bZMtbDsPey0bTsh+Q==","assets/images/wild-times-for-export-2-676x380.jpg":"HATElo1mtrLv+Dle+9Mdvw==","assets/images/dsc09752-676x380.jpg":"UiWm/cY6Wq5Bhlr5l7twCQ==","assets/images/wild-times-for-export-6-676x380.jpeg":"bm3zegXuM35+PfhpguXUqQ==","assets/images/wildlife-africa-final-676x380.jpg":"B766n2E7Tx4mpQrrbCA4RQ==","assets/images/wild-times-for-export-4-676x380.jpg":"2nAKND4x71mzH855zo4yGg==","assets/images/wildlife-africa-final-6-676x380.jpg":"P9sMGEbtKmbMei2l0Adfvw==","assets/images/wildlife-africa-final-2-676x38011.jpg":"UXUbqZJCtF0TrSxXVP3Rmw==","assets/images/screenshot-2022-08-04-at-12.04.20-676x380.jpg":"o74rBfwwdLMywnOOXoatbw==","assets/images/screenshot-2022-08-04-at-12.03.05-676x380.jpg":"iC3DTM3Jocdy/u+bgv3ATA==","assets/images/screenshot-2021-01-07-at-16.16.04-556x313.png":"Nz29Osa+6xBCmtoTdxwkFg==","assets/images/screenshot-2021-01-07-at-16.07.02-copy-556x313.jpg":"TkdRva0bNnvw5GOsELPKOQ==","assets/images/screenshot-2021-01-07-at-16.05.59-copy-556x313.jpg":"07c6vPyqzSw1ZJQcZlTjQg==","assets/images/screenshot-2021-01-07-at-16.06.23-copy-556x313.jpg":"Q+fs1dTS0na1Gvks5nxFcw==","assets/images/screenshot-2021-01-08-at-10.01.06-edit-556x313.jpg":"hSIw9iKRIWWS9ENEq8SQhQ==","assets/images/screenshot-2021-01-08-at-10.01.28-556x313.jpg":"XSaJgoV2aJnCM5/TptXcMg==","assets/images/screenshot-2021-01-07-at-16.15.14-556x313.png":"SZF8ky1a7+NvcG2geB3ZcQ==","assets/images/screenshot-2021-01-08-at-10.01.50-556x313.jpg":"WqVeg2NanFnXd1AjgRMfSQ==","assets/images/dsc07050-1052x1575.jpg":"02vPrqbkPi0KO7akV3sz4A==","assets/images/dsc06259-864x577.jpg":"6pKx3LpiOQJqr4k/453MoA==","assets/images/loveness-nswulu-1576x1053.jpg":"wD7WTSy5j0Vkqc/dZaEHiw==","assets/images/dsc06510-1034x691.jpg":"f9IG8edsn9fEamR/Lt4QkA==","assets/images/alice-haeobwe-656x982.jpg":"z6WJ1ldf49yrJd9fOdiSTQ==","assets/images/screenshot-2021-01-07-at-16.15.34-556x313.png":"jY6KpYuYhlezPvLz+l8qnw==","assets/images/dsc06305-676x1014.jpg":"lvtz2gbwcqTaneVec50/sQ==","assets/images/dsc06662-676x1012.jpg":"GJ/Y0G+cgqoyv4e8JNtaVA==","assets/images/dsc06856-714x1069.jpg":"SJxI8M45NM9q2IrTCihssg==","assets/images/dsc06816-998x1494.jpg":"9I8DZw9nJec1Vd7scGWmqg==","assets/images/dsc06679-1104x1653.jpg":"75uIc1GRrTimw0RsXsqIgQ==","assets/images/screenshot-2022-08-04-at-12.04.49-676x380.jpg":"cT61ccXDYMVwJmRaMR1xYg==","assets/images/dsc06710-1082x723.jpg":"bI4+QOh5ZeWacj1C2JJ2eQ==","assets/images/mary-hagande-962x1440.jpg":"LMbbk9exI22rkCk7SQdhvQ==","assets/images/dsc06809-1576x1053.jpg":"VXfg70rtccyKc/HNbrJjBw==","assets/images/dsc06653-676x1012.jpg":"f0ijlcbGVGA0usiA/miVRQ==","assets/images/dsc07684-944x1413.jpg":"Gtb4JEQmyu2etgaj3VCXAA==","assets/images/dsc07960-1004x1503.jpg":"bDWDFb0ibtl802p8YraGfw==","assets/images/dsc07666-946x1416.jpg":"9TOILUtrbk6HWPHVf1FWDg==","assets/images/dsc07827-996x1491.jpg":"dRHGkK4f8ivJ+Ge3gV8RJw==","assets/images/dsc07718-944x1413.jpg":"tp2wTbVLZNtIzvjE0Ofzkg==","assets/images/mary-hagande-750x1123.jpg":"N68kFs+9Ys7VRMWEn1alog==","assets/images/dsc07733-854x1279.jpg":"wt8uDl89UlsoH2OhY09xag==","assets/images/dsc07913-904x604.jpg":"unvd6qsy2lQBFqdQUtSwxw==","assets/images/dsc07722-804x1204.jpg":"g6b0Hw617OHXXp310HiNAw==","assets/images/1-810x1213.jpg":"5k9LVbJt9wgR9Q3fhgrEMg==","assets/images/dsc07914-1118x1674.jpg":"dk6Hwf7hWPIJNwadL72RcA==","assets/images/dsc07588-860x573.jpg":"LJMgtB96zJ35+lZWgTlh8w==","assets/images/dsc07556-680x1018.jpg":"ADWqhAVykXxDAFpVV2eFYQ==","assets/images/dsc07796-842x1261.jpg":"n8IfgnT7WbTzFj5GaNNksg==","assets/images/dsc07833-970x1452.jpg":"4Q7aADYGl5rBE3TnX8USPg==","assets/images/story-838x1257.jpg":"Jh8kV/lwOqeBsSGk3fEy+w==","assets/images/dsc07921-964x1443.jpg":"sXiHVZ84dbotKH1jtPq5KA==","assets/images/rockpool-856x1282.jpg":"Tx+T3JRiMc/YsHhwzAIwaA==","assets/images/dsc08832-1320x1977.jpg":"4o5D8dOYtRt4IYcHHoFNLg==","assets/images/dsc08474-1020x1530.jpg":"1PD4uVVrNqSnZe5IVkE95Q==","assets/images/dsc08560-634x949.jpg":"Br/3O+1/OHx9j/r3kIPCmA==","assets/images/dsc07904-668x1000.jpg":"WmkO8L8THaf6RaVtI4ZmWg==","assets/images/dsc08521-634x949.jpg":"JD9v1Q7h4Ip8/Tm0ks8wzQ==","assets/images/dsc09280-1-996x1491.jpg":"kdCA9rSBbV9wGM3gPxNBtg==","assets/images/dsc09383-1004x1503.jpg":"/f1bIgE47c7wjRicPwMfaw==","assets/images/dsc09393-944x1413.jpg":"qWc9XzY4TV3fNi1QPAgUaQ==","assets/images/dsc09319-946x1416.jpg":"Cz8TrA5MWDC/P9x63IvTkg==","assets/images/dsc09264-1-988x1479.jpg":"SMsnmx2v7qJXBaiH/CnX0A==","assets/images/dsc09369-832x1246.jpg":"IKpsKRy9KaKPmCFc4i5TDw==","assets/images/dsc09291-802x1201.jpg":"pKdmNnIswmKJkuvOTJ/Lpw==","assets/images/dsc09397-948x1419.jpg":"NZHZmDu8yQ4TrJGWsbXJYA==","assets/images/dsc09375-942x1410.jpg":"vzisFRlXG61LC1c4EbZiSQ==","assets/images/dsc09549-829x1241.jpg":"MRp5OqS0fq042cVHRkeZHA==","assets/images/dsc09565-1170x1752.jpg":"9GyCL2V4cZOZlXyOGA9T8Q==","assets/images/dsc09504-1159x1735.jpg":"dv+V7vBO/wPvQilEdRLNgg==","assets/images/dsc09370-1198x1794.jpg":"cfN2ipE7fe1QSRM0KNTUdA==","assets/images/dsc09540-730x1093.jpg":"+22k2/htwEW7cUtlS0/+2Q==","assets/images/dsc09499-890x1333.jpg":"A4TEudbBqZBtn/mBaf0D6g==","assets/images/dsc09392-990x1482.jpg":"YP85bXOYOxH4ybItz2MoBA==","assets/images/dsc09464-1087x1627.jpg":"dMHRYs3u8UTlaLu4cvTU1g==","assets/images/dsc09562-1776x1186.jpg":"VuJJpEGRqye1zJ9t2Ru0iA==","assets/images/dsc09343-1324x884.jpg":"mD2iM+Mfx5nwz3BpyNKXiw==","assets/images/dsc09604-1156x1731.jpg":"hKxY0rtTvF3VZsskOAI+sg==","assets/images/img-470-1104x736.jpg":"4CPjJfBeVxLb5J3wIeZF0A==","assets/images/dsc09603-844x1264.jpg":"aozdk+fZcBtKHkZz4L7u/A==","assets/images/img-408-1104x1656.jpg":"LFjxWy02iDCLMUCq1+WycA==","assets/images/maya1-1-1088x1632.jpg":"aqJB0jplwlSjaJh6oqg6FA==","assets/images/maya-1-856x1284.jpg":"4RI7qCoHkoiaMnJa1EpmNA==","assets/images/img-420-1092x1637.jpg":"vMOK7vn/u8t7eTZLWdt39g==","assets/images/adorned-15-963x542.jpg":"C4PZLniivv454zYF+f3MbQ==","assets/images/adorned-7-1576x887.jpg":"MxbY2Lp9DJnOhfjtDE0jMg==","assets/images/adorned-18-970x546.jpg":"r9v1TxcxROfgnjiDNnfEdA==","assets/images/adorned-17-801x451.jpg":"kSz1qE1DPzWU9VvaX1j5sA==","assets/images/adorned-4-1304x734.jpg":"SbiTVZMUH3BN6y+bifRTNw==","assets/images/adorned-6-851x479.jpg":"oPnlbvA0zr4CrmjwS4Wp+A==","assets/images/img-468-620x413.jpg":"VbX5kjbp0Og8nb4yoPWLRw==","assets/images/img-391-1092x1638.jpg":"xgl2vEYzDlMMqlMlD3G0kA==","assets/images/img-432-620x930.jpg":"I9GSA9wpoJuQ8RVOLt9A8g==","assets/images/adorned-11-1198x674.jpg":"TFc/qUALZl3S3FxSvjqnaA==","assets/images/adorned-12-1397x786.jpg":"G2MKYHYcKFEHva3aJ8kDTw==","assets/images/adorned-19-758x426.jpg":"L1zZTsDuWS2v9mJhK6t2HQ==","assets/images/adorned-2-993x559.jpg":"oJLEG9yWNoN2Rnoje+uZYw==","assets/images/dsc00463-1276x1910.jpg":"WsOV4vYm9Cdvzxynbh+bjA==","assets/images/adorned-20-1274x717.jpg":"C0pzIra8QQOSUz4vIW/r2w==","assets/images/dsc00469-1238x1854.jpg":"+3awXcpAEhUc0Z/xGrv3rg==","assets/images/dsc00416-1140x1707.jpg":"0dfvc8Y1/gllJW5N4by7gg==","assets/images/dsc00505-905x1355.jpg":"uFgDtyMdEkskaiPQVpbVtg==","assets/images/adorned-8-719x404.jpg":"Y1uQo7c/rjuCS90rpppmVg==","assets/images/dsc00600-972x1455.jpg":"sqTUdIZBrShfJhcnye1cLw==","assets/images/dsc00583-1389x2080.jpg":"WCznXBzdbm+T1AgrcMmGrQ==","assets/images/dsc00492-1215x1819.jpg":"4dOLgnDNQphaK/MLsQf63Q==","assets/images/dsc00591-784x1174.jpg":"az5tkWQjYUcgKYo9lWzldA==","assets/images/dsc00551-1056x1581.jpg":"UKbQ/c0lxxJX4SBau6j/gA==","assets/images/dsc00595-1274x1907.jpg":"y6q3+bhkbq/KO4RGGF2+nA==","assets/images/dsc00389-1287x1927.jpg":"FzJ83DO9F446f7Hpx8ATQA==","assets/images/dsc00475-868x1300.jpg":"FMoPb1OB/UcSTcBJB4gFWg==","assets/images/adorned-9-881x496.jpg":"QNwY4/cA3L71EqLllUZoZg==","assets/images/dsc00523-1250x1875.jpg":"/MStDzDSoPehqQlv6PoAUg==","assets/images/dsc00526-905x1355.jpg":"7uhm5e6UjdZ9GjcyZmeQjA==","assets/images/dsc09772-913x1367.jpg":"QGuDo1msn+kHjmN66ZC/OQ==","assets/images/dsc09728-1302x870.jpg":"2U3A3Pp/B7OQfiHWwSJP0w==","assets/images/dsc09714-1376x919.jpg":"pm1w+q3vQhm/F3TKWFBvBA==","assets/images/dsc09711-1151x769.jpg":"TVob5vzSim/KJQcnzjv3WQ==","assets/images/dsc09819-1064x1593.jpg":"KSYhkALr4Sn4owf64tUarA==","assets/images/dsc09820-1302x870.jpg":"9ptU9OC9RH/0A5h4DNHQUQ==","assets/images/dsc00002-1000x1497.jpg":"whVbhr7xUbicTTc+gZha7w==","assets/images/dsc00146-1-958x1434.jpg":"Cd9zqY4IGiM8HsxJo4byxw==","assets/images/dsc09704-1257x840.jpg":"4p5N+LKLeZofenq0RivRHw==","assets/images/dsc00203-1-913x1367.jpg":"nVQC1PdbJpPWNcbmZXEpSw==","assets/images/dsc09752-1576x1053.jpg":"nO/csrW3vf0IerrmHrJmCA==","assets/images/dsc00210-1000x1497.jpg":"ZhaOHl5a97sao8ppYX+AEw==","assets/images/dsc00663-1-913x1367.jpg":"9WxahvNiPCrrqnQLjSHXfg==","assets/images/dsc00668-1000x668.jpg":"bi6onkTWcPL+ZPidO+0+jQ==","assets/images/dsc09770-958x1434.jpg":"OcJmLKY/jHAyKlAEYCrnNQ==","assets/images/dsc00070-832x1246.jpg":"+oITCzdfanUhdU/FbTfHoQ==","assets/images/dsc00500-1000x1497.jpg":"AO/BXEZtYo2v7xc0k5BJUw==","assets/images/dsc00093-3-913x1367.jpg":"8D+FY2g+UOYtPgX0fxW81Q==","assets/images/dsc00161-715x1070.jpg":"hdCjkliz5koXxAJcrh9Szg==","assets/images/dsc09940-1000x1497.jpg":"xivSJBf0jVXVUh94LqLpcA==","assets/images/dsc00237-1000x668.jpg":"lgT5VW8LwpWxgTpnkGKCkw==","assets/images/dsc09892-657x984.jpg":"GyEZOjBRjkXT9RmqE1AeLw==","assets/images/dsc00181-882x1320.jpg":"gM66EMLnDKYLLtuFBXHfgw==","assets/images/dsc09786-1000x1497.jpg":"zbswjf1w2fJJ2ly6Ayph+Q==","assets/images/dsc09791-918x1374.jpg":"uPVEKT4o6ih2bQ90OoNCpQ==","assets/images/dsc01619-2-913x1367.jpg":"xtFgcuvaVgU2CAXJbrX5zw==","assets/images/dsc09795-913x1367.jpg":"whV1v7qf0llFHk6sgBZ0HQ==","assets/images/dsc01602-1-913x1370.jpg":"9rmya6+URu6Rjp1n3T8G0Q==","assets/images/dsc01581-1-913x1367.jpg":"NXgCj3nj31FT7yaNLOxlGg==","assets/images/dsc01592-1-1302x1949.jpg":"oTf3YNECuOo0fcI+47xMmQ==","assets/images/dsc01542-1000x668.jpg":"1O31pWRSFBWvZ+r+tvgJ1g==","assets/images/dsc01259-1080x721.jpg":"vXtzsIWRkWfvZgtqEuLKCQ==","assets/images/dsc09769-1000x1500.jpg":"nsNUasr8O1joIltLFYhWXA==","assets/images/dsc09868-882x1320.jpg":"6qi70sw/ZsONmeK3bsaAnQ==","assets/images/dsc00023-913x1367.jpg":"E55qEi17qLcysJ+rRZa7AA==","assets/images/dsc00026-1000x1497.jpg":"KDqMDg0lvaAy3I7BDv87tA==","assets/images/dsc00731-913x1367.jpg":"cvI7OwkmuOw3vkEPuoF2gw==","assets/images/dsc00744-1000x1497.jpg":"zi95/MPKci6sjZm3YflH0g==","assets/images/dsc09757-741x1109.jpg":"26hyzrCjEbeAXWVPswx7Og==","assets/images/dsc09803-970x1452.jpg":"f9ni369XommPkolV4BSlFQ==","assets/images/pamoja.00-00-15-20.still008-1920x1080.jpg":"Oae0h/rnD8F9/bT5PdLUiQ==","assets/images/together.00-01-24-14.still015-1920x1080.jpg":"EHWIw88oBbyMmTriTamf0g==","assets/images/sections.00-00-57-05.still011-1920x1080.jpg":"UtUtRFYxce3CPBsHj0mzqg==","assets/images/pamoja.00-00-22-05.still002-1920x1080.jpg":"MtD2XN7mY+LGKdzHgXyyBg==","assets/images/amaranthine-skincare-2000x1125.jpg":"AFvT+vktzdViTAWu9Pw27w==","assets/images/testing-luts.00-01-37-20.still009-1920x1080.jpg":"S/k+n8kW2CHlhSTxmh+htQ==","assets/images/safari-1-1920x1080.jpg":"2h/CXM/O+btPAzToeiI/rw==","assets/images/instagram-version.00-00-06-07.still001-1920x1080.jpg":"N3KuAlxtujK0MpznyKDp+Q==","assets/images/5-1920x1080.jpg":"63BQaGpKi4nTQloQgRBxiw==","assets/images/ajiri-tea-and-coffee.00-00-16-16.still001-1920x10800.jpg":"6Z4HdDFbNcBrnhUcvtqdtA==","assets/images/img-1602-2000x1125.jpg":"P0dKIzBjWLh0hDx9Zyu5eQ==","assets/images/pollination-project-sequence.00-00-33-00.still003-1920x1080.jpg":"cKouFz0TYb9HrGz59NKbug==","assets/images/20200319-southafrica-6-2000x1125.jpg":"FaMoRgZNRlkCNdpd8QrD5w==","assets/images/dsc03376-2000x1336.jpg":"cnqiYbxjaYx0vTDSnld/4Q==","assets/images/trial.00-01-16-02.still004-1920x1080.jpg":"MybeanqVzi89ihWORpogmg==","assets/images/dsc04017-2000x1336.jpg":"kl0sFzVQBixL5/Ea+LBCUw==","assets/images/dsc03869-2000x1333.jpg":"BK2RvAPMC85JMoHjIx5o1Q==","assets/images/screenshot-2021-01-08-at-09.59.29-copy-2000x1125.jpg":"FrnID8/Ps/Akc/XdAQdw7g==","assets/images/dsc01025-2000x1125.jpg":"kyyvCbWRPLcKxej15aRNJw==","assets/images/alfonsina-sinaimbwe.-2000x1336.jpg":"251relwHlZ220BcyioF4PQ==","assets/images/together.00-00-05-19.still001-1920x1080.jpg":"IVxfmbZ4lJtsoFXULJTM8Q==","assets/images/dsc07912-2000x1336.jpg":"6hxpV+kwqa+x+xBL9BwcWg==","assets/images/dsc00703-1-2000x1336.jpg":"9QWHLSI28NVHL1OFlFXEEw==","assets/images/dsc09294-2-2000x1333.jpg":"EIUfPCAtH34JmUZDu1w7bw==","assets/images/dsc09556-2000x2994.jpg":"b1WdCGkQTBkD8Xi6LiDRRA==","assets/images/screenshot-2022-08-04-at-11.43.27-2000x1107.jpg":"gbZVi6UCXk+c9UtMCr7BCw==","assets/images/screenshot-2022-08-04-at-12.00.48-2000x1250.png":"ghPX/+YdGu/n+7tAYTr4yA==","assets/images/dsc09718-2000x1336.jpg":"XSfej2arzfLzBbVobHG/JQ==","assets/images/dsc09860-1000x1497.jpg":"ONV+YsgoS7oeQ6ZEsi404g==","assets/images/mkale-school-video2-1920x1080.jpeg":"igfPzt/O8mgaCqjeep2ZDw==","assets/images/dsc02671-copy-2000x1336.jpeg":"t7CHsO12KNyCt2GgOONxkA==","assets/images/wild-times-for-export-1-1920x1080.jpg":"xXC39+5fNaM+Xbnw/87/ug==","assets/images/adorned-20-2000x1125.jpg":"BEs1nrGASgF5SbRMKOP34g==","assets/images/pamoja.00-02-26-20.still005-1920x1080.jpg":"2K6nt4CjX/y9zos3ZqIFxw==","assets/images/screenshot-2021-01-08-at-10.10.40-2000x1125.jpg":"/Ji9fI4Z6c17Qo85jda8PA==","assets/images/mkale-school-video2-1-1920x1080.jpeg":"igfPzt/O8mgaCqjeep2ZDw==","assets/images/instagram-version.00-00-06-07.still001-1920x108012.jpg":"N3KuAlxtujK0MpznyKDp+Q==","assets/images/together.00-00-05-19.still001-1920x108013.jpg":"IVxfmbZ4lJtsoFXULJTM8Q==","assets/images/pollination-project-sequence.00-00-33-00.still003-1920x108014.jpg":"cKouFz0TYb9HrGz59NKbug==","assets/fonts/MunjiFont-Regular/font.ttf":"Lz3VjO6k79hu3vS9Z2XNVg==","assets/fonts/MunjiFont-Regular/style.css":"pGLtyvY5MEEO9ucNkSuw6A==","assets/images/african-bats-sequence.00-00-25-09.still003-676x38015.jpg":"4ZjH1fIx3QWu6FwFruh2cQ==","assets/images/wildlife-africa-final-2-676x38016.jpg":"UXUbqZJCtF0TrSxXVP3Rmw==","assets/images/instagram-version.00-00-06-07.still001-1920x108017.jpg":"N3KuAlxtujK0MpznyKDp+Q==","assets/images/together.00-00-05-19.still001-1920x108018.jpg":"IVxfmbZ4lJtsoFXULJTM8Q==","assets/images/pollination-project-sequence.00-00-33-00.still003-1920x108019.jpg":"cKouFz0TYb9HrGz59NKbug==","assets/images/african-bats-sequence.00-00-25-09.still003-676x38020.jpg":"4ZjH1fIx3QWu6FwFruh2cQ==","assets/images/wildlife-africa-final-2-676x38021.jpg":"UXUbqZJCtF0TrSxXVP3Rmw==","assets/images/together.00-00-05-19.still001-1920x108023.jpg":"IVxfmbZ4lJtsoFXULJTM8Q==","assets/images/instagram-version.00-00-06-07.still001-1920x108022.jpg":"N3KuAlxtujK0MpznyKDp+Q==","assets/images/pollination-project-sequence.00-00-33-00.still003-1920x108024.jpg":"cKouFz0TYb9HrGz59NKbug==","assets/images/african-bats-sequence.00-00-25-09.still003-676x38025.jpg":"4ZjH1fIx3QWu6FwFruh2cQ==","assets/images/wildlife-africa-final-2-676x38026.jpg":"UXUbqZJCtF0TrSxXVP3Rmw==","assets/images/together.00-00-05-19.still001-1920x108028.jpg":"IVxfmbZ4lJtsoFXULJTM8Q==","assets/images/pollination-project-sequence.00-00-33-00.still003-1920x108029.jpg":"cKouFz0TYb9HrGz59NKbug==","assets/images/instagram-version.00-00-06-07.still001-1920x108027.jpg":"N3KuAlxtujK0MpznyKDp+Q==","assets/images/african-bats-sequence.00-00-25-09.still003-676x38035.jpg":"4ZjH1fIx3QWu6FwFruh2cQ==","assets/images/wildlife-africa-final-2-676x38036.jpg":"UXUbqZJCtF0TrSxXVP3Rmw==","assets/images/instagram-version.00-00-06-07.still001-1920x108037.jpg":"N3KuAlxtujK0MpznyKDp+Q==","assets/images/together.00-00-05-19.still001-1920x108038.jpg":"IVxfmbZ4lJtsoFXULJTM8Q==","assets/images/pollination-project-sequence.00-00-33-00.still003-1920x108039.jpg":"cKouFz0TYb9HrGz59NKbug=="},"github://munjiri/munjirivideos":{}}